add_mul/__init__.py
add_mul/addmul.py
add_mul_test-0.1.0.dist-info/METADATA
add_mul_test-0.1.0.dist-info/WHEEL
add_mul_test-0.1.0.dist-info/top_level.txt
add_mul_test-0.1.0.dist-info/RECORD
